{
    "type": "FeatureCollection",
    "features": [
        {
            "type": "Feature",
            "geometry": {
                "type": "Point",
                "coordinates": [
                    4.7138,
                    50.8823
                ]
            },
            "properties": {
                "appName": "Facebook",
                "usageType": "precise",
                "interactionType": "foreground",
                "timestamp": "2024-03-17 10:02:00"
            }
        }
    ]
}